odoo/addons/helpdesk_ticket_partner_response/README.rst
odoo/addons/helpdesk_ticket_partner_response/__init__.py
odoo/addons/helpdesk_ticket_partner_response/__manifest__.py
odoo/addons/helpdesk_ticket_partner_response/i18n/ca.po
odoo/addons/helpdesk_ticket_partner_response/i18n/es.po
odoo/addons/helpdesk_ticket_partner_response/i18n/helpdesk_ticket_partner_response.pot
odoo/addons/helpdesk_ticket_partner_response/i18n/it.po
odoo/addons/helpdesk_ticket_partner_response/i18n/lv.po
odoo/addons/helpdesk_ticket_partner_response/i18n/pt_BR.po
odoo/addons/helpdesk_ticket_partner_response/i18n/tr.po
odoo/addons/helpdesk_ticket_partner_response/models/__init__.py
odoo/addons/helpdesk_ticket_partner_response/models/helpdesk_ticket.py
odoo/addons/helpdesk_ticket_partner_response/models/helpdesk_ticket_team.py
odoo/addons/helpdesk_ticket_partner_response/models/mail_thread.py
odoo/addons/helpdesk_ticket_partner_response/readme/CONFIGURE.md
odoo/addons/helpdesk_ticket_partner_response/readme/CONTRIBUTORS.md
odoo/addons/helpdesk_ticket_partner_response/readme/DESCRIPTION.md
odoo/addons/helpdesk_ticket_partner_response/readme/USAGE.md
odoo/addons/helpdesk_ticket_partner_response/static/description/icon.png
odoo/addons/helpdesk_ticket_partner_response/static/description/icon.svg
odoo/addons/helpdesk_ticket_partner_response/static/description/index.html
odoo/addons/helpdesk_ticket_partner_response/tests/__init__.py
odoo/addons/helpdesk_ticket_partner_response/tests/test_partner_response.py
odoo/addons/helpdesk_ticket_partner_response/views/helpdesk_ticket_team.xml
odoo_addon_helpdesk_ticket_partner_response-18.0.1.0.0.5.dist-info/METADATA
odoo_addon_helpdesk_ticket_partner_response-18.0.1.0.0.5.dist-info/WHEEL
odoo_addon_helpdesk_ticket_partner_response-18.0.1.0.0.5.dist-info/top_level.txt
odoo_addon_helpdesk_ticket_partner_response-18.0.1.0.0.5.dist-info/RECORD
